Workbook

Sheet Accueil
B2: DUERP AZUR PARK 2026 — AUDIT RISC-4 PAR CATÉGORIE
B3: Classeur de pilotage des 839 critères de l'audit sécurité des personnes — 9 catégories de risque
B5: Établissement | C5: Azur Park — RD 598A — 83580 GASSIN
B6: Téléphone | C6: 06 22 76 79 40
B7: Email | C7: lunapark@wanadoo.fr
B8: Responsable Sécurité | C8: Sam PAILLON
B9: Consultant | C9: David MUSEUR (RiskAttitude / SECURE)
B10: Plateforme DUERP | C10: RISC-4 — DUE en ligne
B11: Référence DUERP | C11: DUERP-AZP-2026-V1 (DOCX consolidé)
B12: Date d'établissement | C12: Avril 2026
B13: Note globale 2024 | C13: 17,54 / 20 — Risque faible ou maîtrisé
B16: MODE D'EMPLOI
B17: 1. | C17: Naviguer | D17: Utiliser les onglets en bas du classeur — un onglet par catégorie de risque + un récapitulatif.
B18: 2. | C18: Filtrer | D18: Cliquer sur les flèches en haut des colonnes pour filtrer (par exemple : voir uniquement les statuts « Non »).
B19: 3. | C19: Renseigner | D19: Pour chaque critère : choisir un statut dans la liste déroulante (Oui / Non / Sans objet / À évaluer), saisir une date, un pilote, une échéance et un commentaire.
B20: 4. | C20: Codes statut | D20: Oui = conforme ; Non = non-conformité à traiter ; Sans objet = ne s'applique pas ; À évaluer = en attente.
B21: 5. | C21: Statistiques | D21: L'onglet « Récapitulatif » se met à jour automatiquement à chaque modification — taux de conformité par catégorie.
B22: 6. | C22: Pièces jointes | D22: Préciser dans la colonne « Preuve / pièce jointe » la référence du document de preuve (rapport, photo, attestation, registre…).
B23: 7. | C23: Réévaluation | D23: À reprendre annuellement avant la saison (mai-juin) avec David MUSEUR — tracer la date de revue dans la colonne « Date d'évaluation ».
B26: LÉGENDE DES STATUTS
B27: Oui | C27: Conforme — pas d'action requise
B28: Non | C28: Non-conformité — action corrective à planifier
B29: Sans objet | C29: Critère non applicable à l'activité
B30: À évaluer | C30: Statut non encore tranché — visite ou décision en attente

Sheet Récapitulatif
A1: RÉCAPITULATIF — TABLEAU DE BORD AUDIT RISC-4
A2: Mise à jour automatique selon les statuts saisis dans les onglets de catégorie
A4: # | B4: Catégorie de risque | C4: Critères | D4: Note 2024 | E4: Oui | F4: Non | G4: Sans objet | H4: À évaluer | I4: Taux conformité
A5: 1 | B5: Risques biologiques | C5: 45 | D5: Non noté | E5: =COUNTIF('1.Biologiques'!D5:D49,"Oui") -> 0 | F5: =COUNTIF('1.Biologiques'!D5:D49,"Non") -> 0 | G5: =COUNTIF('1.Biologiques'!D5:D49,"Sans objet") -> 0 | H5: =COUNTIF('1.Biologiques'!D5:D49,"À évaluer") -> 0 | I5: =IFERROR(E5/(E5+F5),"-") -> -
A6: 2 | B6: Risques routiers | C6: 35 | D6: 19,56/20 | E6: =COUNTIF('2.Routiers'!D5:D39,"Oui") -> 0 | F6: =COUNTIF('2.Routiers'!D5:D39,"Non") -> 0 | G6: =COUNTIF('2.Routiers'!D5:D39,"Sans objet") -> 0 | H6: =COUNTIF('2.Routiers'!D5:D39,"À évaluer") -> 0 | I6: =IFERROR(E6/(E6+F6),"-") -> -
A7: 3 | B7: Risques chimiques | C7: 77 | D7: 18,27/20 | E7: =COUNTIF('3.Chimiques'!D5:D81,"Oui") -> 0 | F7: =COUNTIF('3.Chimiques'!D5:D81,"Non") -> 0 | G7: =COUNTIF('3.Chimiques'!D5:D81,"Sans objet") -> 0 | H7: =COUNTIF('3.Chimiques'!D5:D81,"À évaluer") -> 0 | I7: =IFERROR(E7/(E7+F7),"-") -> -
A8: 4 | B8: Risques d'incendie et d'explosion | C8: 101 | D8: 17,84/20 | E8: =COUNTIF('4.Incendie-Explosion'!D5:D105,"Oui") -> 0 | F8: =COUNTIF('4.Incendie-Explosion'!D5:D105,"Non") -> 0 | G8: =COUNTIF('4.Incendie-Explosion'!D5:D105,"Sans objet") -> 0 | H8: =COUNTIF('4.Incendie-Explosion'!D5:D105,"À évaluer") -> 0 | I8: =IFERROR(E8/(E8+F8),"-") -> -
A9: 5 | B9: Risques psycho-sociaux | C9: 103 | D9: 16,83/20 | E9: =COUNTIF('5.Psycho-sociaux'!D5:D107,"Oui") -> 0 | F9: =COUNTIF('5.Psycho-sociaux'!D5:D107,"Non") -> 0 | G9: =COUNTIF('5.Psycho-sociaux'!D5:D107,"Sans objet") -> 0 | H9: =COUNTIF('5.Psycho-sociaux'!D5:D107,"À évaluer") -> 0 | I9: =IFERROR(E9/(E9+F9),"-") -> -
A10: 6 | B10: Risques des manutentions manuelles et mécaniques | C10: 112 | D10: 16,86/20 | E10: =COUNTIF('6.Manutentions'!D5:D116,"Oui") -> 0 | F10: =COUNTIF('6.Manutentions'!D5:D116,"Non") -> 0 | G10: =COUNTIF('6.Manutentions'!D5:D116,"Sans objet") -> 0 | H10: =COUNTIF('6.Manutentions'!D5:D116,"À évaluer") -> 0 | I10: =IFERROR(E10/(E10+F10),"-") -> -
A11: 7 | B11: Risques physiques | C11: 147 | D11: 17,05/20 | E11: =COUNTIF('7.Physiques'!D5:D151,"Oui") -> 0 | F11: =COUNTIF('7.Physiques'!D5:D151,"Non") -> 0 | G11: =COUNTIF('7.Physiques'!D5:D151,"Sans objet") -> 0 | H11: =COUNTIF('7.Physiques'!D5:D151,"À évaluer") -> 0 | I11: =IFERROR(E11/(E11+F11),"-") -> -
A12: 8 | B12: Risques des circulations et déplacements | C12: 91 | D12: 19,56/20 | E12: =COUNTIF('8.Circulations'!D5:D95,"Oui") -> 0 | F12: =COUNTIF('8.Circulations'!D5:D95,"Non") -> 0 | G12: =COUNTIF('8.Circulations'!D5:D95,"Sans objet") -> 0 | H12: =COUNTIF('8.Circulations'!D5:D95,"À évaluer") -> 0 | I12: =IFERROR(E12/(E12+F12),"-") -> -
A13: 9 | B13: Organisation interne de l'entreprise | C13: 128 | D13: 15,60/20 | E13: =COUNTIF('9.Organisation interne'!D5:D132,"Oui") -> 0 | F13: =COUNTIF('9.Organisation interne'!D5:D132,"Non") -> 0 | G13: =COUNTIF('9.Organisation interne'!D5:D132,"Sans objet") -> 0 | H13: =COUNTIF('9.Organisation interne'!D5:D132,"À évaluer") -> 0 | I13: =IFERROR(E13/(E13+F13),"-") -> -
B14: TOTAL | C14: =SUM(C5:C13) -> 839 | D14: 17,54/20 | E14: =SUM(E5:E13) -> 0 | F14: =SUM(F5:F13) -> 0 | G14: =SUM(G5:G13) -> 0 | H14: =SUM(H5:H13) -> 0 | I14: =IFERROR(E14/(E14+F14),"-") -> -
A17: INDICATEURS GLOBAUX
B18: Total questions | E18: =C14 -> 839
B19: Questions conformes (Oui) | E19: =E14 -> 0
B20: Non-conformités (Non) | E20: =F14 -> 0
B21: Questions sans objet | E21: =G14 -> 0
B22: Questions à évaluer | E22: =H14 -> 0
B23: Taux de conformité global | E23: =I14 -> -
B24: Taux de complétude (Oui+Non+SO) | E24: =IFERROR((E14+F14+G14)/C14,"-") -> 0

Sheet 1.Biologiques
A1: RISQUES BIOLOGIQUES
A2: Note RISC-4 (DUE 2024) : Non noté — Établissement : Azur Park (Gassin) — Référentiel : audit sécurité des personnes
A4: N° | B4: Référence | C4: Question / Critère | D4: Statut | E4: Date d'évaluation | F4: Pilote | G4: Échéance / Action | H4: Preuve / pièce jointe | I4: Commentaire / observations
A5: 1 | B5: BIO-001 | C5: L'entreprise connaît-elle la classification des différents agents biologiques ?
A6: 2 | B6: BIO-002 | C6: L'entreprise a-t-elle déterminé la nature, la durée et les conditions de l'exposition des travailleurs pour tous les postes de travail présentant un risque d'exposition à des agents biologiques ?
A7: 3 | B7: BIO-003 | C7: En fonction de la classe de risques encourus, l'entreprise a-t-elle procédé à une déclaration d'utilisation d'agents pathogènes à l'inspecteur régional d'hygiène et de sécurité ?
A8: 4 | B8: BIO-004 | C8: Une liste de travailleurs concernés par l'exposition aux agents de groupes 3 et 4 a-t-elle été communiquée au médecin de prévention ?
A9: 5 | B9: BIO-005 | C9: Chaque travailleur exposé à des agents biologiques pathogènes a-t-il un dossier médical spécial tenu par le médecin du travail ?
A10: 6 | B10: BIO-006 | C10: Une fiche d'exposition pour chaque travailleur exposé à des risques biologiques a-t-elle été mise en place ?
A11: 7 | B11: BIO-007 | C11: L'employeur informe-t-il le médecin du travail en cas d'absences pour cause de maladie des travailleurs exposés à des agents biologiques pathogènes ?
A12: 8 | B12: BIO-008 | C12: Dans le cas de l'apparition d'une infection chez un travailleur, le personnel susceptible d'avoir été exposé fait-il l'objet d'un examen médical ?
A13: 9 | B13: BIO-009 | C13: L'entreprise a-t-elle réfléchi à la possibilité de remplacer certains agents biologiques dangereux par d'autres qui le seraient moins ?
A14: 10 | B14: BIO-010 | C14: Les méthodes de travail et les règles de prévention des risques biologiques sont-elles connues et comprises des travailleurs exposés et de leur responsable ?
A15: 11 | B15: BIO-011 | C15: Les retours d'expérience permettent-ils de mettre à jour les documentations ?
A16: 12 | B16: BIO-012 | C16: Un groupe de travail sur les AES a-t-il été mis en place ?
... A49: 45 | B49: BIO-045 | C49: Des animaux (chats, chiens, rats, etc.) ont-ils accès au local d'entreposage des déchets biologiques ?

Sheet 2.Routiers
A1: RISQUES ROUTIERS
A2: Note RISC-4 (DUE 2024) : 19,56/20 — Établissement : Azur Park (Gassin) — Référentiel : audit sécurité des personnes
A4: N° | B4: Référence | C4: Question / Critère | D4: Statut | E4: Date d'évaluation | F4: Pilote | G4: Échéance / Action | H4: Preuve / pièce jointe | I4: Commentaire / observations
A5: 1 | B5: ROU-001 | C5: Le risque d’accident de trajet est-il évalué ?
A6: 2 | B6: ROU-002 | C6: Des travailleurs sont-ils amenés à faire des déplacements piétons dans le cadre de leur travail (pour aller à la poste, faire des courses pour l'entreprise, etc.) ?
A7: 3 | B7: ROU-003 | C7: Existe-t-il un règlement spécifique (ou une charte) des déplacements routiers des travailleurs (conduite en sécurité, interdictions, recommandations, etc.) ?
A8: 4 | B8: ROU-004 | C8: Ce règlement est-il porté à leur connaissance et mis à la disposition des travailleurs ?
A9: 5 | B9: ROU-005 | C9: Les nouveaux travailleurs et/ou les intérimaires utilisant un véhicule de l'entreprise sont-ils informés des consignes de sécurité relatives aux déplacements routiers ?
A10: 6 | B10: ROU-006 | C10: Existe-t-il une liste précise de tous les travailleurs qui utilisent un véhicule routier dans le cadre de leurs fonctions (chauffeur-livreurs, commerciaux, techniciens, etc.) ?
A11: 7 | B11: ROU-007 | C11: Une analyse des déplacements (évolution, fréquence, durée, véhicules utilisés, horaires, etc.) des travailleurs qui utilisent un véhicule routier dans le cadre de leurs fonctions a-t-elle été réalisée ?
A12: 8 | B12: ROU-008 | C12: Les travailleurs exposés sont-ils formés aux gestes de premiers secours ?
A13: 9 | B13: ROU-009 | C13: Les causes d'accidents (s'il y a lieu) ont-elles été analysées, les constats amiables sont-ils étudiés ?
A14: 10 | B14: ROU-010 | C14: L'entreprise organise-t-elle des formations ou des campagnes de prévention aux risques routiers à l'attention des travailleurs ?
A15: 11 | B15: ROU-011 | C15: Les travailleurs exposés sont-ils encouragés à faire des formations pour réactualiser régulièrement leurs connaissances ?
A16: 12 | B16: ROU-012 | C16: Les travailleurs en horaires de nuit ou en travail posté sont-ils sensibilisés aux risques routiers ?
... A39: 35 | B39: ROU-035 | C39: L'employeur interdit-il explicitement aux travailleurs de recourir à des substances alcoolisées ou psychotropes au cours de leurs déplacements pour l'entreprise ?

Sheet 3.Chimiques
A1: RISQUES CHIMIQUES
A2: Note RISC-4 (DUE 2024) : 18,27/20 — Établissement : Azur Park (Gassin) — Référentiel : audit sécurité des personnes
A4: N° | B4: Référence | C4: Question / Critère | D4: Statut | E4: Date d'évaluation | F4: Pilote | G4: Échéance / Action | H4: Preuve / pièce jointe | I4: Commentaire / observations
A5: 1 | B5: CHM-001 | C5: Un inventaire des produits chimiques utilisés dans l'entreprise est-il réalisé et actualisé ?
A6: 2 | B6: CHM-002 | C6: L'entreprise est-elle en possession des documents de sécurité inhérents aux produits utilisés (fiches de données de sécurité (FDS), recommandations des fournisseurs, etc.) ?
A7: 3 | B7: CHM-003 | C7: Les fiches de données de sécurité (FDS) sont-elles transmises au médecin du travail et mises à la disposition des travailleurs (délégués du personnel, CHSCT) ?
A8: 4 | B8: CHM-004 | C8: Les FDS et les étiquettes figurant sur les produits sont-elles rédigées en langue française ?
A9: 5 | B9: CHM-005 | C9: Les préconisations contenues dans les FDS sont-elles prises en compte et respectées (conditions de stockage, d'utilisation, EPI, etc.) ?
A10: 6 | B10: CHM-006 | C10: L'encadrement contrôle-t-il régulièrement que les préconisations contenues dans les FDS sont prises en compte et respectées par les travailleurs ?
A11: 7 | B11: CHM-007 | C11: Les produits utilisés ou manipulés sont-ils tous étiquetés conformément à la législation ?
A12: 8 | B12: CHM-008 | C12: Tous les contenants sont-ils systématiquement identifiés et étiquetés ?
A13: 9 | B13: CHM-009 | C13: Des produits inflammables, toxiques, nocifs, corrosifs ou irritants sont-ils stockés de manière accessible ?
A14: 10 | B14: CHM-010 | C14: Existe-t-il des procédures visant à limiter la durée d'exposition et le nombre de travailleurs exposés aux produits chimiques dangereux ?
A15: 11 | B15: CHM-011 | C15: Existe-t-il une filière et des procédures d'évacuation des déchets ?
A16: 12 | B16: CHM-012 | C16: Le personnel affecté au nettoyage du matériel souillé bénéficie-t-il des EPI appropriés ?
... A81: 77 | B81: CHM-077 | C81: L'employeur pose-t-il des questions à son Service de Santé au travail sur la dangerosité des produits d'entretien courant utilisés ?

Sheet 4.Incendie-Explosion
A1: RISQUES D'INCENDIE ET D'EXPLOSION
A2: Note RISC-4 (DUE 2024) : 17,84/20 — Établissement : Azur Park (Gassin) — Référentiel : audit sécurité des personnes
A4: N° | B4: Référence | C4: Question / Critère | D4: Statut | E4: Date d'évaluation | F4: Pilote | G4: Échéance / Action | H4: Preuve / pièce jointe | I4: Commentaire / observations
A5: 1 | B5: INC-001 | C5: L'entreprise a-t-elle établi et affiché d'une manière très apparente dans tous ses locaux l'ensemble des consignes concernant la lutte contre l'incendie ?
A6: 2 | B6: INC-002 | C6: L'entreprise tient-elle un registre incendie ?
A7: 3 | B7: INC-003 | C7: En cas d'intervention d'une entreprise extérieure, un permis de feu est-il systématiquement délivré ?
A8: 4 | B8: INC-004 | C8: L'entreprise vérifie-t-elle que les travailleurs respectent les consignes de sécurité (stockage de matières inflammables, papiers, etc.) ?
A9: 5 | B9: INC-005 | C9: L'entreprise est-elle située dans un IGH ?
A10: 6 | B10: INC-006 | C10: L'entreprise est-elle bien en conformité avec les directives concernant la prévention incendie dans les IGH ?
A11: 7 | B11: INC-007 | C11: L'entreprise a-t-elle établi un inventaire de tous les produits combustibles présents et utilisés dans l'entreprise ?
A12: 8 | B12: INC-008 | C12: L'entreprise a-t-elle établi une liste de tous les travailleurs utilisant des combustibles, comburants ou explosifs ?
A13: 9 | B13: INC-009 | C13: Les travailleurs utilisant des combustibles, comburants ou explosifs sont-ils formés à leur utilisation ?
A14: 10 | B14: INC-010 | C14: Les travailleurs utilisant des combustibles, comburants ou explosifs sont-ils informés des risques ?
A15: 11 | B15: INC-011 | C15: Un responsable est-il désigné pour gérer l'utilisation des combustibles, comburants ou explosifs ?
A16: 12 | B16: INC-012 | C16: Existe-t-il une interdiction explicite concernant l'utilisation des combustibles, comburants ou explosifs par les travailleurs non habilités ?
... A105: 101 | B105: INC-101 | C105: Des moyens de lutte contre l'incendie autre que les extincteurs sont-ils présents et suivi dans l'entreprise ?

Sheet 5.Psycho-sociaux
A1: RISQUES PSYCHO-SOCIAUX
A2: Note RISC-4 (DUE 2024) : 16,83/20 — Établissement : Azur Park (Gassin) — Référentiel : audit sécurité des personnes
A4: N° | B4: Référence | C4: Question / Critère | D4: Statut | E4: Date d'évaluation | F4: Pilote | G4: Échéance / Action | H4: Preuve / pièce jointe | I4: Commentaire / observations
A5: 1 | B5: RPS-001 | C5: L'employeur et/ou l'encadrement prennent-ils en compte les remarques des travailleurs ou de l'encadrement concernant l'organisation de travail (charge de travail, cadences, stress, interlocuteurs multiples, horaires, contrainte du public, etc.) ?
A6: 2 | B6: RPS-002 | C6: L'employeur connaît-il les conséquences de la fatigue, du surmenage, du stress, etc. sur la santé et la sécurité des travailleurs ?
A7: 3 | B7: RPS-003 | C7: L'entreprise a-t-elle consulté le médecin de travail afin d'obtenir des informations sur la notion de charge mentale (fatigue, stress, etc.) et de ses conséquences sur la santé des travailleurs ?
A8: 4 | B8: RPS-004 | C8: L'entreprise a-t-elle un surcroît d'activité à certaines périodes de la journée et/ou à certaines périodes de l'année ?
A9: 5 | B9: RPS-005 | C9: D'une manière générale, les travailleurs subissant un surcroît de travail sont-ils aidés par les autres travailleurs (répartition des tâches par exemple) ?
A10: 6 | B10: RPS-006 | C10: Certains travailleurs travaillent-ils à la chaîne, en cadences élevées et/ou répètent-ils continuellement une même série de gestes ou d'opérations ?
A11: 7 | B11: RPS-007 | C11: Les travailleurs qui travaillent à la chaîne, en cadences élevées et/ou qui répètent continuellement un geste ou une même série de gestes ou d'opérations bénéficient-ils de pauses ?
A12: 8 | B12: RPS-008 | C12: La durée des pauses et leur fréquence sont-elles suffisantes pour permettre la récupération nécessaire ?
A13: 9 | B13: RPS-009 | C13: Les travailleurs qui travaillent à la chaîne, en cadences élevées et/ou qui répètent continuellement une même série de gestes ont-ils la possibilité d'influer sur le rythme de leur travail (par exemple arrêter la machine lorsqu'ils ne peuvent plus suivre) et/ou d'interrompre momentanément leur travail ?
A14: 10 | B14: RPS-010 | C14: Certains travailleurs travaillent-ils en flux tendu et/ou en juste-à-temps (livraisons, service à la clientèle, etc.) ?
A15: 11 | B15: RPS-011 | C15: L'entreprise emploie-t-elle des travailleurs en travail de nuit ?
A16: 12 | B16: RPS-012 | C16: Certains postes de travail impliquent-ils des horaires de travail irréguliers ?
... A107: 103 | B107: RPS-103 | C107: Les changements sont-ils suffisamment anticipés, accompagnés, et clairement expliqués aux salariés ?

Sheet 6.Manutentions
A1: RISQUES DES MANUTENTIONS MANUELLES ET MÉCANIQUES
A2: Note RISC-4 (DUE 2024) : 16,86/20 — Établissement : Azur Park (Gassin) — Référentiel : audit sécurité des personnes
A4: N° | B4: Référence | C4: Question / Critère | D4: Statut | E4: Date d'évaluation | F4: Pilote | G4: Échéance / Action | H4: Preuve / pièce jointe | I4: Commentaire / observations
A5: 1 | B5: MAN-001 | C5: Des travailleurs sont-ils amenés à effectuer des manutentions manuelles de charges (chargement et déchargement de marchandises, transport de colis, etc.) ?
A6: 2 | B6: MAN-002 | C6: Existe-t-il des tâches, liées aux manutentions manuelles de charges, imposant des gestes répétitifs avec contraintes posturales et/ou imposant le maintien prolongé d'une posture ?
A7: 3 | B7: MAN-003 | C7: Existe-t-il des tâches imposant des manutentions difficiles, répétitives et/ou à cadence élevée ?
A8: 4 | B8: MAN-004 | C8: Existe-t-il des manutentions pour les opérations de transport ou de soutien de la charge dont le levage, la pose, la poussée, la traction, le port ou le déplacement exige l'effort physique d'une ou plusieurs personnes ?
A9: 5 | B9: MAN-005 | C9: Certains travailleurs sont-ils amenés à porter longtemps de petites charges (par exemple les commerciaux qui transportent des échantillons ou des documentations, le personnel qui effectue des démonstrations de matériel, etc.) ?
A10: 6 | B10: MAN-006 | C10: Certains travailleurs sont-ils amenés à manutentionner (stocker et/ou transporter) des matières, agents chimiques dangereux et/ou des déchets contenant de tels agents ?
A11: 7 | B11: MAN-007 | C11: Tous les postes de manutention manuelle de charges dans l'entreprise sont-ils recensés ?
A12: 8 | B12: MAN-008 | C12: L'entreprise utilise-t-elle des aides à la manutention pour déplacer les charges lourdes et/ou encombrantes (aides au soulèvement des charges, équilibreurs de charges, vérins, palans, tables élévatrices, chariots, transpalettes, convoyeurs, rouleaux, rolls, trolleys, ponts de liaison, etc.) ?
A13: 9 | B13: MAN-009 | C13: L'entreprise a-t-elle fait une analyse détaillée des postes concernés par les manutentions manuelles (pénibilité, répétitivité des gestes, caractéristiques des charges manipulées, effort physique, fréquence des efforts, environnement de travail, organisation du travail, etc.) ?
A14: 10 | B14: MAN-010 | C14: L'entreprise a-t-elle prévu un projet d'amélioration visant à supprimer et à réduire les manutention manuelles (aide à la manutention, organisation des postes, etc.) et/ou des aménagements (dispositifs de mise à hauteur, tables élévatrices, etc.) ?
A15: 11 | B15: MAN-011 | C15: Un responsable a-t-il été désigné et formé pour mener à bien le projet d'amélioration des postes de travail concernés par les manutentions manuelles de charges ?
A16: 12 | B16: MAN-012 | C16: L'employeur connaît-il les risques des manutentions manuelles de charges sur la santé et la sécurité des travailleurs ?
... A116: 112 | B116: MAN-112 | C116: Un protocole des manutentions et/ou de chargement et déchargement de charges a-t-il été établi avec chaque entreprise extérieure ?

Sheet 7.Physiques
A1: RISQUES PHYSIQUES
A2: Note RISC-4 (DUE 2024) : 17,05/20 — Établissement : Azur Park (Gassin) — Référentiel : audit sécurité des personnes
A4: N° | B4: Référence | C4: Question / Critère | D4: Statut | E4: Date d'évaluation | F4: Pilote | G4: Échéance / Action | H4: Preuve / pièce jointe | I4: Commentaire / observations
A5: 1 | B5: PHY-001 | C5: L'entreprise a-t-elle mesuré le niveau d'exposition sonore quotidien (bruit des machines, armoires réseau, air comprimé, outils portatifs, etc.) et la valeur de pression acoustique de crête auxquels est soumis chaque travailleur de l'entreprise au cours de son travail ?
A6: 2 | B6: PHY-002 | C6: Les mesures de bruit, si elles ont été faites, sont-elles répertoriées dans un document comportant les postes de travail mesurés, la période de la mesure du bruit et la méthode adoptée ?
A7: 3 | B7: PHY-003 | C7: Les opérations de mesures de bruit, si elles ont été faites, datent-elles de moins de trois ans ?
A8: 4 | B8: PHY-004 | C8: Les mesures de bruit, si elles ont été faites, ont-elles été réalisées en collaboration avec l'ensemble des travailleurs concernés ?
A9: 5 | B9: PHY-005 | C9: L'entreprise connaît-elle la charge sonore de tous les postes de travail de l'entreprise ?
A10: 6 | B10: PHY-006 | C10: Tous les travailleurs exposés au bruit sont-ils recensés ?
A11: 7 | B11: PHY-007 | C11: L'entreprise a-t-elle identifié tous les travailleurs (ou postes de travail) pour lesquels l'exposition sonore quotidienne atteint ou dépasse le niveau de 85 dB(A) ou pour lesquels la pression acoustique de crête dépasse le niveau de 130 dB ?
A12: 8 | B12: PHY-008 | C12: Certains travailleurs dans l'entreprise sont-ils soumis à un niveau de bruit supérieur à 85 dB(A) sans protections d'oreilles ?
A13: 9 | B13: PHY-009 | C13: Certaines activités ou machines occasionnent-elles un bruit continu ?
A14: 10 | B14: PHY-010 | C14: Les postes de travail, les appareils et les zones où on relève un bruit continu et/ou dangereux pour l'ouïe sont-ils indiqués par la signalétique ''protections d'oreilles obligatoires'' ?
A15: 11 | B15: PHY-011 | C15: Les travailleurs exposés au bruit disposent-ils des EPI (protections d'oreilles notamment) nécessaires ?
A16: 12 | B16: PHY-012 | C16: L'encadrement vérifie-t-il régulièrement que les EPI sont portés par les travailleurs exposés au bruit ?
... A151: 147 | B151: PHY-147 | C151: Les interventions effectuées sur les matériels informatiques sont-elles inscrites sur les carnets d'entretien ?

Sheet 8.Circulations
A1: RISQUES DES CIRCULATIONS ET DÉPLACEMENTS
A2: Note RISC-4 (DUE 2024) : 19,56/20 — Établissement : Azur Park (Gassin) — Référentiel : audit sécurité des personnes
A4: N° | B4: Référence | C4: Question / Critère | D4: Statut | E4: Date d'évaluation | F4: Pilote | G4: Échéance / Action | H4: Preuve / pièce jointe | I4: Commentaire / observations
A5: 1 | B5: CIR-001 | C5: Un responsable est-il nommé pour organiser la circulation en sécurité des travailleurs au sein de l'entreprise (signalétique, nettoyage, entretien et/ou déneigement, etc. des voies de circulation, des escaliers, des portes et portails) ?
A6: 2 | B6: CIR-002 | C6: Les personnel de l'entreprise amené à se déplacer sur les voies de circulation des piétons porte-t-il des chaussures maintenant bien le pied et munies de semelles antidérapantes ?
A7: 3 | B7: CIR-003 | C7: Existe-t-il dans l'entreprise des dispositifs de signalisation (panneau ''danger'' par exemple) signalant les dangers temporaires de faux pas et/ou de glissade, ou pour isoler une zone dangereuse ?
A8: 4 | B8: CIR-004 | C8: Les portes se trouvant dans les voies de circulation s'ouvrent-elles dans le sens de l'évacuation ?
A9: 5 | B9: CIR-005 | C9: Les mesures nécessaires à l'élimination des risques lors de l'utilisation des portes et des portails ont-elles été prises (par exemple, sécurisation des passage pour piétons débouchant directement sur une voie de circulation, risque inattendu de heurt ou collision dissimulé par une porte, zone propice aux chutes, contact violent de personnes ou de véhicules avec une porte en mouvement, etc.) ?
A10: 6 | B10: CIR-006 | C10: Les zones propices aux coincements (pincements, cisaillements, blessures, etc.) situées entre les portes et les parties fixes du bâtiment sont-elles sécurisées ?
A11: 7 | B11: CIR-007 | C11: Les portes coulissantes sont-elles sécurisées contre les chutes, c'est-à-dire qu'elles ne possèdent ni seuil, ni butée, ni marche, etc.
A12: 8 | B12: CIR-008 | C12: Est-ce que toutes les installations motorisées de porte ou portail sont équipées d'un interrupteur de sécurité ?
A13: 9 | B13: CIR-009 | C13: Les fenêtres de l'entreprise sont-elles toutes munies d'une balustrade ? L'entretien et le contrôle des éléments de sécurité des fenêtres sont-ils régulièrement effectués ?
A14: 10 | B14: CIR-010 | C14: Les voies de circulation des piétons (couloirs, escaliers, voies d'accès, voies de dégagement, etc.) sont-elles bien délimitée et signalisées ?
A15: 11 | B15: CIR-011 | C15: Les voies de circulation des piétons sont-elles planes (sans trous, inégalités, dénivellations, aspérités, etc.) ? Les sols sont-ils lisses et exempts de crevasses, rainures, arrêtes et d'autres éléments pouvant entraîner un faux pas ou une chute ?
A16: 12 | B16: CIR-012 | C16: Les marches, les seuils, etc. qui ne peuvent être évités sont-ils clairement signalés et toujours bien visibles et éclairés ?
... A95: 91 | B95: CIR-091 | C95: Les travailleurs des entreprises extérieures qui sont amenés à intervenir dans l'entreprise sont-ils formés et informés, dès leur arrivée, des consignes de sécurité en vigueur dans l'entreprise ?

Sheet 9.Organisation interne
A1: ORGANISATION INTERNE DE L'ENTREPRISE
A2: Note RISC-4 (DUE 2024) : 15,60/20 — Établissement : Azur Park (Gassin) — Référentiel : audit sécurité des personnes
A4: N° | B4: Référence | C4: Question / Critère | D4: Statut | E4: Date d'évaluation | F4: Pilote | G4: Échéance / Action | H4: Preuve / pièce jointe | I4: Commentaire / observations
A5: 1 | B5: ORG-001 | C5: Les numéros d'urgence sont-ils affichés bien en vue dans l'entreprise ?
A6: 2 | B6: ORG-002 | C6: Les coordonnées de votre Service de Santé au Travail sont-elles affichées dans l'entreprise ?
A7: 3 | B7: ORG-003 | C7: Existe-t-il un panneau d'affichage à l'attention des travailleurs concernant la sécurité au travail (affiches et brochure du service de santé au travail, formations, noms du ou des responsables sécurité, consignes de sécurité...) ?
A8: 4 | B8: ORG-004 | C8: L'entreprise a-t-elle mis en place une formation spécifique pour les travailleurs illettrés, ou ne parlant pas le français, afin qu'ils puissent reconnaître les étiquettes, panneaux d'avertissement, etc. ?
A9: 5 | B9: ORG-005 | C9: L'entreprise veille-t-elle à ce que les travailleurs illettrés, ou ne parlant pas le français, reçoivent une formation spécifique sur les règles de sécurité et/ou d'utilisation des matériels ?
A10: 6 | B10: ORG-006 | C10: L'entreprise s'assure-t-elle que les connaissances des règles de sécurité des travailleurs illettrés, ou ne parlant pas le français, sont régulièrement actualisées ?
A11: 7 | B11: ORG-007 | C11: L'entreprise veille-t-elle à ce que les travailleurs handicapés reçoivent une formation spécifique sur les règles de sécurité et/ou d'utilisation des matériels adaptée à leur handicap ?
A12: 8 | B12: ORG-008 | C12: S'il existe des délégués ou représentants des travailleurs dans l'entreprise sont-ils sensibilisés au management des risques ?
A13: 9 | B13: ORG-009 | C13: Les partenaires hygiène-sécurité (CHSCT, SST, médecin du travail, délégués du personnel, etc.) de l'entreprise sont-ils connus nominativement et les informations les concernant (coordonnées) sont-elles affichées ?
A14: 10 | B14: ORG-010 | C14: Existe-t-il des échanges d'informations réguliers entre le médecin du travail et l'employeur ?
A15: 11 | B15: ORG-011 | C15: Le médecin du travail a-t-il établi la fiche d'entreprise relative aux risques professionnels ?
A16: 12 | B16: ORG-012 | C16: Existe-t-il un Registre Hygiène Sécurité dans lequel sont consignés les incidents, accidents, blessures, observations... survenus dans l'entreprise ?
... A132: 128 | B132: ORG-128 | C132: L'employeur organise-t-il des réunions sur la sécurité dans l'entreprise avec le personnel d'encadrement et les travailleurs (comité de sécurité, auto-contrôle des travailleurs, travailleurs ''tuteurs'', etc.) ?
